{
 "cells": [
  {
   "cell_type": "code",
   "execution_count": 2,
   "id": "243a8d7c-c973-48d3-8ae5-f2aec075efb4",
   "metadata": {},
   "outputs": [
    {
     "name": "stdout",
     "output_type": "stream",
     "text": [
      "This is count 1\n",
      "This is count 2\n",
      "This is count 3\n",
      "This is count 4\n",
      "This is count 5\n",
      "A fruit of type: apples\n",
      "A fruit of type: oranges\n",
      "A fruit of type: pears\n",
      "A fruit of type: apricots\n",
      "I got 1\n",
      "I got pennies\n",
      "I got 2\n",
      "I got dimes\n",
      "I got 3\n",
      "I got quarters\n",
      "Adding 0 to the list\n",
      "Adding 1 to the list\n",
      "Adding 2 to the list\n",
      "Adding 3 to the list\n",
      "Adding 4 to the list\n",
      "Adding 5 to the list\n",
      "Element was: 0\n",
      "Element was: 1\n",
      "Element was: 2\n",
      "Element was: 3\n",
      "Element was: 4\n",
      "Element was: 5\n",
      "  0           0 RESUME                   0\n",
      "\n",
      "  2           2 LOAD_NAME                0 (the_count)\n",
      "              4 GET_ITER\n",
      "        >>    6 FOR_ITER                13 (to 34)\n",
      "              8 STORE_NAME               1 (number)\n",
      "\n",
      "  3          10 PUSH_NULL\n",
      "             12 LOAD_NAME                2 (print)\n",
      "             14 LOAD_NAME                1 (number)\n",
      "             16 PRECALL                  1\n",
      "             20 CALL                     1\n",
      "             30 POP_TOP\n",
      "             32 JUMP_BACKWARD           14 (to 6)\n",
      "\n",
      "  2     >>   34 LOAD_CONST               0 (None)\n",
      "             36 RETURN_VALUE\n"
     ]
    }
   ],
   "source": [
    "#in simple terms, a for-loop in Python helps you repeat a task for each item in a collection, \n",
    "#making it easier to work with multiple pieces of data without having to write the same code over and over again.\n",
    "\n",
    "the_count = [1, 2, 3, 4, 5]\n",
    "fruits = ['apples', 'oranges', 'pears', 'apricots']\n",
    "change = [1, 'pennies', 2, 'dimes', 3, 'quarters']\n",
    "\n",
    "#this first kind of for loop goes through a list. \n",
    "#I think of it like, \"for each number in the list calle \"the_count\" print a string with the current number, then repeat in order until the list is completed. \n",
    "for number in the_count:\n",
    "    print(f\"This is count {number}\")\n",
    "\n",
    "#same as above\n",
    "for fruit in fruits:\n",
    "    print(f\"A fruit of type: {fruit}\")\n",
    "\n",
    "#also we can go through mixed lists too\n",
    "for i in change:\n",
    "    print(f\"I got {i}\")\n",
    "\n",
    "#we can also build lists. First start with an empty one.\n",
    "elements = []\n",
    "\n",
    "#then use the range() function to do 0 to 5 counts.\n",
    "#a range defines where to start and stop in a list but remember the \"stop\" is -1 before and the start is 0 (not 1)\n",
    "for i in range(0, 6):\n",
    "    print(f\"Adding {i} to the list\")\n",
    "    #append is a function that lists understand\n",
    "    elements.append(i)\n",
    "\n",
    "for i in elements:\n",
    "    print(f\"Element was: {i}\")\n",
    "\n",
    "from dis import dis\n",
    "\n",
    "dis('''\n",
    "for number in the_count:\n",
    "    print(number)\n",
    "''')"
   ]
  },
  {
   "cell_type": "code",
   "execution_count": null,
   "id": "cca072e3-32f1-4ec1-8284-7940e2949c0f",
   "metadata": {},
   "outputs": [],
   "source": []
  }
 ],
 "metadata": {
  "kernelspec": {
   "display_name": "Python 3 (ipykernel)",
   "language": "python",
   "name": "python3"
  },
  "language_info": {
   "codemirror_mode": {
    "name": "ipython",
    "version": 3
   },
   "file_extension": ".py",
   "mimetype": "text/x-python",
   "name": "python",
   "nbconvert_exporter": "python",
   "pygments_lexer": "ipython3",
   "version": "3.11.7"
  }
 },
 "nbformat": 4,
 "nbformat_minor": 5
}
